setup.py
sleekbasebot/__init__.py
sleekbasebot/decorators.py
sleekbasebot/sleekbasebot.py
sleekbasebot.egg-info/PKG-INFO
sleekbasebot.egg-info/SOURCES.txt
sleekbasebot.egg-info/dependency_links.txt
sleekbasebot.egg-info/requires.txt
sleekbasebot.egg-info/top_level.txt
sleekbasebot/commands/__init__.py
sleekbasebot/commands/help.py
sleekbasebot/commands/muc.py
sleekbasebot/muc_logging/__init__.py
sleekbasebot/muc_logging/muc_logging.py