Metadata-Version: 1.1
Name: sleekbasebot
Version: 0.0.2
Summary: basic sleekxmpp bot with argument parsing and muc logging
Home-page: https://github.com/puhoy/sleekbasebot
Author: Jan Hartmann
Author-email: stuff@kwoh.de
License: MIT
Keywords: xmpp,sleekxmpp,bot
Platform: UNKNOWN
Classifier: Development Status :: 3 - Alpha
Classifier: Intended Audience :: Developers
Classifier: Topic :: Software Development :: Build Tools
Classifier: License :: OSI Approved :: MIT License
Classifier: Programming Language :: Python
Classifier: Programming Language :: Python :: 2
Classifier: Programming Language :: Python :: 2.6
Classifier: Programming Language :: Python :: 2.7
Classifier: Programming Language :: Python :: 3
Classifier: Programming Language :: Python :: 3.2
Classifier: Programming Language :: Python :: 3.3
Classifier: Programming Language :: Python :: 3.4
Classifier: Operating System :: OS Independent
